setup.py
networkconfgen/__init__.py
networkconfgen/base.py
networkconfgen/constants.py
networkconfgen/custom_filters.py
networkconfgen.egg-info/PKG-INFO
networkconfgen.egg-info/SOURCES.txt
networkconfgen.egg-info/dependency_links.txt
networkconfgen.egg-info/requires.txt
networkconfgen.egg-info/top_level.txt