Metadata-Version: 1.1
Name: networkconfgen
Version: 0.2.0
Summary: Jinja2 based configuration generator with some extensions required to generate configurations for network devices
Home-page: https://github.com/hoelsner/networkconfgen
Author: Henry Ölsner
Author-email: henry@codingnetworker.com
License: MIT
Platform: UNKNOWN
Classifier: Development Status :: 4 - Beta
Classifier: Intended Audience :: Developers
Classifier: Intended Audience :: System Administrators
Classifier: Topic :: System :: Networking
Classifier: License :: OSI Approved :: MIT License
Classifier: Programming Language :: Python :: 2
Classifier: Programming Language :: Python :: 2.7
Classifier: Programming Language :: Python :: 3
Classifier: Programming Language :: Python :: 3.4
Classifier: Programming Language :: Python :: 3.5
Classifier: Programming Language :: Python :: 3.6
